vkts/__init__.py
vkts/admreal.py
vkts/main.py
vkts/real.py
vkts/report.py
vkts/usrdata.py
vkts/utils.py
vkts/vklib/__init__.py
vkts/vklib/hotreqs.py
vkts/vklib/packs.py
vkts/vklib/vkauth.py
vkts/vklib/vkobjs.py
vkts/vklib/vkreq.py
vkts-0.0.6.dist-info/LICENSE
vkts-0.0.6.dist-info/METADATA
vkts-0.0.6.dist-info/WHEEL
vkts-0.0.6.dist-info/entry_points.txt
vkts-0.0.6.dist-info/top_level.txt
vkts-0.0.6.dist-info/RECORD
