Metadata-Version: 2.1
Name: vkts
Version: 0.0.6
Summary: Library of accelerated access to vk API & thematic students search tool
Home-page: https://github.com/smurphik/vkts
Author: Denis Stepnov
Author-email: stepnovdenis@gmail.com
License: MIT
Keywords: vk social network web scraping
Platform: UNKNOWN
Classifier: Development Status :: 2 - Pre-Alpha
Classifier: Topic :: Internet :: WWW/HTTP
Classifier: Environment :: Console
Classifier: License :: OSI Approved :: MIT License
Requires-Dist: requests
Requires-Dist: pytest
